.svnignore
setup.cfg
setup.py
DBSprockets.egg-info/PKG-INFO
DBSprockets.egg-info/SOURCES.txt
DBSprockets.egg-info/dependency_links.txt
DBSprockets.egg-info/entry_points.txt
DBSprockets.egg-info/not-zip-safe
DBSprockets.egg-info/requires.txt
DBSprockets.egg-info/top_level.txt
dbsprockets/__init__.py
dbsprockets/decorators.py
dbsprockets/iprovider.py
dbsprockets/metadata.py
dbsprockets/primitives.py
dbsprockets/saprovider.py
dbsprockets/sessionconfig.py
dbsprockets/sprockets.py
dbsprockets/util.py
dbsprockets/validatorselector.py
dbsprockets/view.py
dbsprockets/viewconfig.py
dbsprockets/viewfactory.py
dbsprockets/widgetselector.py
dbsprockets/dbmechanic/__init__.py
dbsprockets/dbmechanic/resources.py
dbsprockets/dbmechanic/frameworks/__init__.py
dbsprockets/dbmechanic/frameworks/pylons/__init__.py
dbsprockets/dbmechanic/frameworks/pylons/dbmechanic.py
dbsprockets/dbmechanic/frameworks/pylons/templates/__init__.py
dbsprockets/dbmechanic/frameworks/pylons/templates/index.html
dbsprockets/dbmechanic/frameworks/pylons/templates/master.html
dbsprockets/dbmechanic/frameworks/pylons/templates/tableView.html
dbsprockets/dbmechanic/frameworks/pylons/templates/tw_resources.html
dbsprockets/dbmechanic/frameworks/tg/__init__.py
dbsprockets/dbmechanic/frameworks/tg/dbmechanic.py
dbsprockets/dbmechanic/frameworks/tg/templates/__init__.py
dbsprockets/dbmechanic/frameworks/tg/templates/index.html
dbsprockets/dbmechanic/frameworks/tg/templates/master.html
dbsprockets/dbmechanic/frameworks/tg/templates/picker.html
dbsprockets/dbmechanic/frameworks/tg/templates/primitives.html
dbsprockets/dbmechanic/frameworks/tg/templates/register.html
dbsprockets/dbmechanic/frameworks/tg/templates/sitetemplate.html
dbsprockets/dbmechanic/frameworks/tg/templates/tableView.html
dbsprockets/dbmechanic/frameworks/tg/templates/tw_resources.html
dbsprockets/dbmechanic/frameworks/tg2/__init__.py
dbsprockets/dbmechanic/frameworks/tg2/dbmechanic.py
dbsprockets/dbmechanic/frameworks/tg2/public/css/dbmechanic.css
dbsprockets/dbmechanic/frameworks/tg2/templates/__init__.py
dbsprockets/dbmechanic/frameworks/tg2/templates/edit.html
dbsprockets/dbmechanic/frameworks/tg2/templates/index.html
dbsprockets/dbmechanic/frameworks/tg2/templates/master.html
dbsprockets/dbmechanic/frameworks/tg2/test/TG2TestApp/TG2TestApp.egg-info/PKG-INFO
dbsprockets/dbmechanic/frameworks/tg2/test/TG2TestApp/TG2TestApp.egg-info/SOURCES.txt
dbsprockets/dbmechanic/frameworks/tg2/test/TG2TestApp/TG2TestApp.egg-info/dependency_links.txt
dbsprockets/dbmechanic/frameworks/tg2/test/TG2TestApp/TG2TestApp.egg-info/entry_points.txt
dbsprockets/dbmechanic/frameworks/tg2/test/TG2TestApp/TG2TestApp.egg-info/paste_deploy_config.ini_tmpl
dbsprockets/dbmechanic/frameworks/tg2/test/TG2TestApp/TG2TestApp.egg-info/paster_plugins.txt
dbsprockets/dbmechanic/frameworks/tg2/test/TG2TestApp/TG2TestApp.egg-info/requires.txt
dbsprockets/dbmechanic/frameworks/tg2/test/TG2TestApp/TG2TestApp.egg-info/top_level.txt
