Metadata-Version: 1.0
Name: DBSprockets
Version: 0.2.1-r380
Summary: A package for creation of web widgets directly from database definitions.
Home-page: http://dbsprockets.googlecode.com/svn/dist
Author: Christopher Perkins Michael Brickenstein 2007-2008
Author-email: chris@percious.com
License: MIT
Platform: UNKNOWN
Classifier: Development Status :: 4 - Beta
Classifier: Intended Audience :: Developers
Classifier: License :: OSI Approved :: MIT License
Classifier: Programming Language :: Python
Classifier: Topic :: Internet :: WWW/HTTP
Classifier: Topic :: Internet :: WWW/HTTP :: Dynamic Content
Classifier: Topic :: Software Development :: Libraries :: Python Modules
